artoo_detoo-0.1.1.dist-info/METADATA
artoo_detoo-0.1.1.dist-info/WHEEL
artoo_detoo-0.1.1.dist-info/entry_points.txt
r2_d2.libs/libcrypto-801de193.so.3
r2_d2.libs/libssl-091d763c.so.3
r2_d2/__init__.py
r2_d2/r2_d2.abi3.so
artoo_detoo-0.1.1.dist-info/RECORD
