Metadata-Version: 2.3
Name: artoo-detoo
Version: 0.1.1
Classifier: Programming Language :: Rust
Classifier: Programming Language :: Python :: Implementation :: CPython
Classifier: Programming Language :: Python :: Implementation :: PyPy
Summary: Simple Client for Cloudflare R2 to manage Restic Backups
Keywords: 
Author-email: Robin van der Noord <robinvandernoord@gmail.com>
License: MIT
Requires-Python: >=3.8
Project-URL: Source Code, https://github.com/robinvandernoord/uvx2
